dario/__init__.py
dario/cli.py
dario-0.0.1.dist-info/entry_points.txt
dario-0.0.1.dist-info/WHEEL
dario-0.0.1.dist-info/METADATA
dario-0.0.1.dist-info/RECORD
