Metadata-Version: 2.1
Name: dario
Version: 0.0.1
Summary: 
Home-page: https://github.com/lukaskubis/dario
Author: Lukáš Kubiš
Author-email: contact@lukaskubis.com
Requires-Python: >=3.7,<4.0
Classifier: Programming Language :: Python :: 3
Classifier: Programming Language :: Python :: 3.7
Classifier: Programming Language :: Python :: 3.8
Provides-Extra: uvloop
Requires-Dist: click (>=7.1.2,<8.0.0)
Requires-Dist: uvloop (>=0.14.0,<0.15.0); extra == "uvloop"
Project-URL: Repository, https://github.com/lukaskubis/dario
